toolio/__about__.py
toolio/__init__.py
toolio/client.py
toolio/common.py
toolio/http_impl.py
toolio/http_schematics.py
toolio/llm_helper.py
toolio/response_helper.py
toolio/schema_helper.py
toolio/toolcall.py
toolio/util.py
toolio/cli/__init__.py
toolio/cli/request.py
toolio/cli/server.py
toolio/tool/__init__.py
toolio/tool/demo.py
toolio/tool/math.py
toolio/tool/schematics.py
toolio/tool/temporal.py
toolio/vendor/__init__.py
toolio/vendor/llm_structured_output/__init__.py
toolio/vendor/llm_structured_output/acceptor.py
toolio/vendor/llm_structured_output/json_acceptor.py
toolio/vendor/llm_structured_output/json_schema_acceptor.py
toolio/vendor/llm_structured_output/util/__init__.py
toolio/vendor/llm_structured_output/util/bitmap.py
toolio/vendor/llm_structured_output/util/output.py
toolio/vendor/llm_structured_output/util/tokenization.py
toolio/vendor/llm_structured_output/util/tokentrie.py
toolio/resource/language.toml
toolio-0.6.0.dist-info/METADATA
toolio-0.6.0.dist-info/WHEEL
toolio-0.6.0.dist-info/entry_points.txt
toolio-0.6.0.dist-info/RECORD
