Metadata-Version: 2.4
Name: Toolio
Version: 0.6.0
Summary: AI API implementation for Mac which supports tool-calling & other structured LLM response generation (e.g. conform to JSON schema)
Project-URL: Documentation, https://OoriData.github.io/Toolio/
Project-URL: Issues, https://github.com/OoriData/Toolio/issues
Project-URL: Source, https://github.com/OoriData/Toolio
Author-email: Uche Ogbuji <uche@oori.dev>
License-Expression: Apache-2.0
Classifier: Development Status :: 4 - Beta
Classifier: Programming Language :: Python
Classifier: Programming Language :: Python :: 3.11
Classifier: Programming Language :: Python :: 3.12
Classifier: Programming Language :: Python :: Implementation :: CPython
Requires-Python: >=3.11
Requires-Dist: click
Requires-Dist: fastapi>=0.115.3
Requires-Dist: httpx>=0.27.2
Requires-Dist: mlx-lm>=0.21.4; sys_platform == 'darwin' and platform_machine == 'arm64' and python_version >= '3.8'
Requires-Dist: mlx>=0.23.1; sys_platform == 'darwin' and platform_machine == 'arm64' and python_version >= '3.8'
Requires-Dist: ogbujipt>=0.9.3
Requires-Dist: uvicorn>=0.32.0
Provides-Extra: dev
Requires-Dist: build; extra == 'dev'
Requires-Dist: pytest-asyncio; extra == 'dev'
Requires-Dist: pytest-httpserver; extra == 'dev'
Provides-Extra: tools
Requires-Dist: google-re2; extra == 'tools'
